Metadata-Version: 1.0
Name: translatex
Version: 0.0.1
Summary: API to convert the file
Home-page: http://github.com/Arashi/translatex
Author: Arashi
Author-email: shtormetsky@gmail.com
License: Apache License version 2.0, see LICENSE file
Platform: UNKNOWN
